fastmodule/__init__.py
fastmodule/common/__init__.py
fastmodule/common/controller.py
fastmodule/common/routes.py
fastmodule/fastmodule.py
fastmodule-0.0.1.dist-info/METADATA
fastmodule-0.0.1.dist-info/WHEEL
fastmodule-0.0.1.dist-info/RECORD
