Metadata-Version: 2.1
Name: fastmodule
Version: 0.0.1
Summary: 
Author: Pablo España
Author-email: pabloespanab@outlook.com
Requires-Python: >=3.10,<4.0
Classifier: Programming Language :: Python :: 3
Classifier: Programming Language :: Python :: 3.10
Classifier: Programming Language :: Python :: 3.11
Requires-Dist: fastapi (>=0.100.0,<0.101.0)
Requires-Dist: uvicorn (>=0.23.1,<0.24.0)
